stellar_contract_bindings/__init__.py
stellar_contract_bindings/cli.py
stellar_contract_bindings/java.py
stellar_contract_bindings/metadata.py
stellar_contract_bindings/python.py
stellar_contract_bindings/utils.py
stellar_contract_bindings-0.4.1b0.dist-info/licenses/LICENSE
stellar_contract_bindings-0.4.1b0.dist-info/METADATA
stellar_contract_bindings-0.4.1b0.dist-info/WHEEL
stellar_contract_bindings-0.4.1b0.dist-info/entry_points.txt
stellar_contract_bindings-0.4.1b0.dist-info/top_level.txt
stellar_contract_bindings-0.4.1b0.dist-info/RECORD
