Metadata-Version: 2.4
Name: stellar-contract-bindings
Version: 0.4.1b0
Summary: CLI tool designed to generate language bindings for Stellar Soroban smart contracts.
Author: overcat
License: Apache-2.0
Project-URL: Homepage, https://github.com/lightsail-network/stellar-contract-bindings
Project-URL: Changelog, https://github.com/lightsail-network/stellar-contract-bindings/releases
Project-URL: Issues, https://github.com/lightsail-network/stellar-contract-bindings/issues
Project-URL: CI, https://github.com/lightsail-network/stellar-contract-bindings/actions
Keywords: stellar,soroban
Requires-Python: >=3.9
License-File: LICENSE
Requires-Dist: black>=24.10.0
Requires-Dist: click>=8.1.7
Requires-Dist: jinja2>=3.1.4
Requires-Dist: stellar-sdk>=12.0.0
Dynamic: license-file
